dataleon/__init__.py
dataleon/_base_client.py
dataleon/_client.py
dataleon/_compat.py
dataleon/_constants.py
dataleon/_exceptions.py
dataleon/_files.py
dataleon/_models.py
dataleon/_qs.py
dataleon/_resource.py
dataleon/_response.py
dataleon/_streaming.py
dataleon/_types.py
dataleon/_version.py
dataleon/py.typed
dataleon/_utils/__init__.py
dataleon/_utils/_logs.py
dataleon/_utils/_proxy.py
dataleon/_utils/_reflection.py
dataleon/_utils/_resources_proxy.py
dataleon/_utils/_streams.py
dataleon/_utils/_sync.py
dataleon/_utils/_transform.py
dataleon/_utils/_typing.py
dataleon/_utils/_utils.py
dataleon/lib/.keep
dataleon/resources/__init__.py
dataleon/resources/companies/__init__.py
dataleon/resources/companies/companies.py
dataleon/resources/companies/documents.py
dataleon/resources/individuals/__init__.py
dataleon/resources/individuals/documents.py
dataleon/resources/individuals/individuals.py
dataleon/types/__init__.py
dataleon/types/company_create_params.py
dataleon/types/company_list_params.py
dataleon/types/company_list_response.py
dataleon/types/company_registration.py
dataleon/types/company_retrieve_params.py
dataleon/types/company_update_params.py
dataleon/types/individual.py
dataleon/types/individual_create_params.py
dataleon/types/individual_list_params.py
dataleon/types/individual_list_response.py
dataleon/types/individual_retrieve_params.py
dataleon/types/individual_update_params.py
dataleon/types/companies/__init__.py
dataleon/types/companies/document_upload_params.py
dataleon/types/individuals/__init__.py
dataleon/types/individuals/document_response.py
dataleon/types/individuals/document_upload_params.py
dataleon/types/individuals/generic_document.py
dataleon/types/shared/__init__.py
dataleon/types/shared/check.py
dataleon_sdk-0.1.0a1.dist-info/METADATA
dataleon_sdk-0.1.0a1.dist-info/WHEEL
dataleon_sdk-0.1.0a1.dist-info/licenses/LICENSE
dataleon_sdk-0.1.0a1.dist-info/RECORD
